colour_print/__init__.py
colour_print/cp.py
colour_print-0.0.2.dist-info/LICENSE
colour_print-0.0.2.dist-info/METADATA
colour_print-0.0.2.dist-info/WHEEL
colour_print-0.0.2.dist-info/top_level.txt
colour_print-0.0.2.dist-info/RECORD
