Metadata-Version: 2.1
Name: colour-print
Version: 0.0.2
Summary: A python package to print coloured output, e.g., for debugging purposes.
Home-page: https://github.com/RaghuSpaceRajan/colour-print-python
Author: ('Raghu Rajan',)
Author-email: rajanr@cs.uni-freiburg.de
License: GNU GPL, Version 3.0
Project-URL: Bug Tracker, https://github.com/RaghuSpaceRajan/colour-print-python/issues
Platform: UNKNOWN
Classifier: Programming Language :: Python :: 3
Classifier: Natural Language :: English
Classifier: Intended Audience :: Developers
Classifier: Intended Audience :: Education
Classifier: Intended Audience :: Science/Research
License-File: LICENSE
